pygifconvt_mg/__init__.py
pygifconvt_mg/converter.py
pygifconvt_mg-1.0.5.dist-info/LICENSE
pygifconvt_mg-1.0.5.dist-info/METADATA
pygifconvt_mg-1.0.5.dist-info/WHEEL
pygifconvt_mg-1.0.5.dist-info/top_level.txt
pygifconvt_mg-1.0.5.dist-info/RECORD
